{
  "piani": [
    {
      "id": "apr2026",
      "label": "Piano Aprile 2026",
      "meta": "23 mar → 26 apr 2026",
      "gara": "10 km — 26 Aprile 2026",
      "current": true
    }
  ],
  "details": {
    "mont1": {
      "title": "Montagna — uscita media · dom 22 mar (già fatto)",
      "body": "<strong>Già eseguita.</strong> Uscita media 4-5h, 800-1200m D+. Equivale a una corsa lunga potenziata con forte componente eccentrica (discesa). Oggi lunedì: mobilità obbligatoria, niente corsa."
    },
    "mob0": {
      "title": "Mobilità/recupero · lun 23 mar",
      "body": "<strong>~20 min — priorità oggi.</strong> World lunge · 90/90 stretch · Downward dog con pompate polpacci · Foam roller quadricipiti e polpacci. Le gambe hanno la discesa di ieri: niente corsa."
    },
    "mob2": {
      "title": "Mobilità · mer 1 apr",
      "body": "<strong>~25 min.</strong> Single-leg deadlift leggerissimo (propriocezione caviglia) · 90/90 · World lunge · Piriforme. Recupero attivo dopo il salto al Lv 7."
    },
    "mob3": {
      "title": "Mobilità · mar 8 apr (priorità alta)",
      "body": "<strong>~25 min · non saltare.</strong> Settimana di picco. Foam roller gambe complete · 5 min respirazione diaframmatica sdraiato (metodo RV) · Ileopsoas stretch se hai tensioni."
    },
    "mob4": {
      "title": "Mobilità · mer 15 apr",
      "body": "<strong>~25 min.</strong> Come sett. 3. Il Lv 9 stanca le gambe: foam roller, 90/90, respirazione diaframmatica. Non saltare."
    },
    "mob5": {
      "title": "Mobilità pre-gara · sab 25 apr",
      "body": "<strong>~20 min · solo dinamica.</strong> Leg swing avanti/dietro e laterali · Intrarotazioni anca · Mobilità caviglia a muro · A-skip leggero. Niente stretching statico prolungato: abbassa il tono muscolare. Dormi bene."
    },
    "r6b": {
      "title": "Corsa — Livello 6 (2ª sessione) · mer 25 mar",
      "body": "<strong>3' camminando + 15' corsa × 3</strong> (~57 min totali). Ritmo conservativo: devi poter parlare per tutta la durata. Respirazione nasale finché regge. Dopo: valuta 1 (facile) / 2 (gestibile) / 3 (dura). Due \"1-2\" consecutivi → sali al Lv 7."
    },
    "r6c_dom": {
      "title": "Corsa Lv 6 (3ª) · dom 29 mar — opzionale",
      "body": "<strong>3' camminando + 15' corsa × 3.</strong> Opzionale: se le gambe sono pesanti, sposta a lunedì 30. Non perdi nulla. Se ti senti bene, falla domenica e lunedì 30 diventa riposo."
    },
    "r6c_lun": {
      "title": "Corsa Lv 6 (3ª) · lun 30 mar — alternativa se dom 29 era riposo",
      "body": "<strong>3' camminando + 15' corsa × 3.</strong> Alternativa a domenica 29. Dopo questa sessione, da martedì 31 si sale al Lv 7. Valutazione 1-2-3 dopo."
    },
    "r7a": {
      "title": "Corsa — Livello 7 (1ª sessione) · mar 31 mar",
      "body": "<strong>5' camminando + 25' corsa × 2.</strong> Il salto da 15' a 25' continui è il più significativo del piano. Parti lento: i primi 5' di ogni blocco sono di assestamento. Non guardare il passo, guarda solo il respiro."
    },
    "r7b": {
      "title": "Corsa — Livello 7 (2ª sessione) · ven 3 apr",
      "body": "<strong>5' camminando + 25' corsa × 2.</strong> Cerca il ritmo che \"scorre\" senza sforzo: quello è il tuo ritmo gara potenziale. Valutazione 1-2-3 dopo."
    },
    "r7c": {
      "title": "Corsa — Livello 7 (3ª sessione) · dom 5 apr",
      "body": "<strong>5' camminando + 25' corsa × 2.</strong> Terza sessione di consolidamento. Se tutte e tre erano \"1-2\", martedì 8 sali al Lv 8 con piena fiducia."
    },
    "r8a": {
      "title": "Corsa — Livello 8 (1ª sessione) · mar 8 apr",
      "body": "<strong>3' camminando + 35' corsa + 5' cammino + 15' corsa.</strong> Struttura nuova: blocco lungo + blocco corto finale. I 35' devono essere corsi a passo facile — il blocco da 15' finale è il vero test. Gambe fresche = lettura affidabile."
    },
    "r8b": {
      "title": "Corsa — Livello 8 (2ª sessione) · gio 10 apr",
      "body": "<strong>3' camminando + 35' corsa + 5' cammino + 15' corsa.</strong> Seconda sessione Lv 8. Se va bene, da lunedì 14 sali al Lv 9. Se era dura, aggiungi una terza sabato 12 in sostituzione della forza B."
    },
    "r9a": {
      "title": "Corsa — Livello 9 (1ª sessione) · mar 14 apr",
      "body": "<strong>5' camminando + 45' corsa + 5' cammino + 15' corsa.</strong> ~70 min di movimento. I 45' continui sono la distanza più lunga del piano. Ritmo conversazionale obbligatorio: se non riesci a parlare, stai andando troppo forte."
    },
    "r9b": {
      "title": "Corsa — Livello 9 (2ª sessione) · ven 17 apr",
      "body": "<strong>5' camminando + 45' corsa + 5' cammino + 15' corsa.</strong> Seconda volta sui 45': dovrebbe sentirsi più gestibile della prima. Da qui la fiducia per la gara è costruita."
    },
    "r9c": {
      "title": "Corsa Lv 9 (3ª, opt.) · dom 19 apr",
      "body": "<strong>5' camminando + 45' corsa + 5' cammino + 15' corsa.</strong> Opzionale: se sei stanco sostituisci con 25-30 min easy. Non serve spingere — la gara è tra 7 giorni."
    },
    "rsca": {
      "title": "Corsa easy · mar 21 apr",
      "body": "<strong>20 min easy + 4×20s strides.</strong> Ritmo lentissimo. Ultimi 5 min: 4 accelerazioni di 20 secondi a ritmo gara con recupero camminando. Tiene vive le fibre veloci senza accumulare stanchezza."
    },
    "rscb": {
      "title": "Corsa pre-gara · ven 24 apr",
      "body": "<strong>15 min easy + 3×20s strides.</strong> Solo schema motorio, niente distanza né ritmo. Stretching dinamico leggero dopo."
    },
    "r10": {
      "title": "🏁 GARA 10 km · dom 26 aprile 2026",
      "body": "<strong>Warm-up 10 min + 10 km.</strong> Strategia: parti al ritmo comodo del Lv 9. Primi 3 km conservativi: lì si decide la gara. Se a 5 km sei fresco, spingi. Piano B sempre valido: run/walk 8'+2' fino al traguardo. Finire è vincere."
    },
    "f1a": {
      "title": "Forza gambe A · mar 24 mar",
      "body": "<span class=\"vol-tag\">Sett. 1 — base</span><br><strong>3 giri · ~30 min · recupero 60s</strong><br>Squat corpo libero 3×12 · Affondi alternati 3×10/lato · Step-up su sedia 3×10/lato · Calf raise 3×15.<br>Nessun peso aggiunto. Focus tecnica e respirazione nasale. È la settimana di adattamento."
    },
    "f1b": {
      "title": "Forza gambe B · gio 26 mar",
      "body": "<span class=\"vol-tag\">Sett. 1 — base</span><br><strong>3 giri · ~30 min · recupero 60s</strong><br>Wall sit 3×30s · Squat con elastico 3×12 · Hip hinge con peso 3×10 · Glute bridge 3×15."
    },
    "f2a": {
      "title": "Forza gambe A · gio 2 apr",
      "body": "<span class=\"vol-tag up\">↑ +10% carico rispetto sett. 1</span><br><strong>3 giri · ~35 min · recupero 50s</strong><br>Squat con pesi 3×12 · Affondi con elastico 3×12/lato (+2 rip/lato) · Step-up alto 3×12/lato (+2 rip/lato) · Single-leg calf raise 3×12.<br>Aggiungi manubri leggeri allo squat. Recupero scende da 60s a 50s."
    },
    "f2b": {
      "title": "Forza gambe B · dom 5 apr (o sab 4)",
      "body": "<span class=\"vol-tag up\">↑ +10% carico rispetto sett. 1</span><br><strong>3 giri · ~35 min · recupero 50s</strong><br>Bulgarian split squat 3×10/lato · Hip hinge con pesi 3×12 · Glute bridge monogamba 3×10/lato · Wall sit 3×40s (+10s).<br>Se le gambe accusano le 3 corse, riduci a 2 giri senza sensi di colpa."
    },
    "f3a": {
      "title": "Forza gambe A · mer 9 apr",
      "body": "<span class=\"vol-tag up\">↑ PICCO — +1 giro + carico massimo</span><br><strong>4 giri · ~40 min · recupero 45s</strong><br>Squat con pesi 4×10 · Affondi cammino con elastico 4×10/lato · Step-up con pesi 4×10/lato.<br>Aumenta il peso dello squat rispetto sett. 2. Recupero scende a 45s. Se arrivi stanco: 3 giri invece di 4."
    },
    "f3b": {
      "title": "Forza gambe B · ven 11 apr",
      "body": "<span class=\"vol-tag up\">↑ PICCO — +1 giro + carico massimo</span><br><strong>4 giri · ~38 min · recupero 45s</strong><br>Bulgarian split squat con pesi 4×10/lato · RDL monogamba 3×10 · Glute bridge con elastico 4×12 · Wall sit 3×50s (+10s)."
    },
    "f4a": {
      "title": "Forza gambe · sab 18 apr",
      "body": "<span class=\"vol-tag\">= carico sett. 2 (mantenimento)</span><br><strong>3 giri · ~30 min · recupero 55s</strong><br>Squat con pesi 3×12 · Affondi con elastico 3×10/lato · Step-up con pesi 3×10/lato.<br>Il volume di corsa (Lv 9) è già alto: la forza mantiene senza sovraccaricare."
    },
    "f5": {
      "title": "Forza gambe scarico · mer 22 apr",
      "body": "<span class=\"vol-tag\">↓ Scarico pre-gara</span><br><strong>2 giri soli · ~20 min · recupero 60s</strong><br>Squat 2×10 leggero · Affondi 2×8/lato · Step-up 2×8/lato.<br>Zero fatica. Finisci la sessione sentendoti esattamente come prima di iniziarla."
    },
    "c1": {
      "title": "Arrampicata · ven 27 mar",
      "body": "<strong>~75 min · tecnica.</strong> Boulder 4a–5b, focus piedi e bilanciamento. Niente potenza. Settimana di rientro dalla montagna: intensità bassa. Termina con 10 min stretching spalle e avambracci."
    },
    "c2": {
      "title": "Arrampicata · sab 4 apr",
      "body": "<strong>~90 min · tecnica/moderata.</strong> Traversi, sequenze tecniche, qualche 5c–6a se ti senti bene. Domani (o ieri) c'è corsa: non esaurire le gambe."
    },
    "c3": {
      "title": "Arrampicata · sab 12 apr",
      "body": "<strong>~75 min · conservativa.</strong> Settimana più carica del piano: mantenimento, non progressione. Vie facili, boulder tecnico. Se venerdì sei già stanco, salta senza rimpianti."
    },
    "c4": {
      "title": "Arrampicata · gio 16 apr",
      "body": "<strong>~75 min · moderata.</strong> Focus su upper body e tecnica. Niente boulder potente sui piedi: il volume di corsa al Lv 9 è già alto."
    },
    "c5": {
      "title": "Arrampicata facile · gio 23 apr",
      "body": "<strong>45 min max · 4a–4c.</strong> Solo per tenere attivo il sistema nervoso. Se le gambe sono pesanti, salta."
    }
  },
  "weeks": [
    {
      "piano": "apr2026",
      "label": "Sett. 1  23–30 mar",
      "note": "Recupero montagna (dom 22/3) + completamento Lv 6. Oggi mobilità obbligatoria. Corsa Lv 6 (3ª) flessibile: dom 29 se ti senti bene, lun 30 se hai bisogno di un giorno extra.",
      "cols": 8,
      "days": [
        {
          "date": "Lun 23/3",
          "isoDate": "2026-03-23",
          "badges": [{ "cls": "b-mob", "txt": "Mobilità recupero", "key": "mob0" }]
        },
        {
          "date": "Mar 24/3",
          "isoDate": "2026-03-24",
          "badges": [{ "cls": "b-forza", "txt": "Forza gambe A", "key": "f1a" }]
        },
        {
          "date": "Mer 25/3",
          "isoDate": "2026-03-25",
          "badges": [{ "cls": "b-run", "txt": "Corsa Lv 6 (2ª)", "key": "r6b" }]
        },
        {
          "date": "Gio 26/3",
          "isoDate": "2026-03-26",
          "badges": [{ "cls": "b-forza", "txt": "Forza gambe B", "key": "f1b" }]
        },
        {
          "date": "Ven 27/3",
          "isoDate": "2026-03-27",
          "badges": [{ "cls": "b-climb", "txt": "Arrampicata", "key": "c1" }]
        },
        {
          "date": "Sab 28/3",
          "isoDate": "2026-03-28",
          "badges": [],
          "rest": true
        },
        {
          "date": "Dom 29/3",
          "isoDate": "2026-03-29",
          "alt": true,
          "badges": [{ "cls": "b-opt", "txt": "Lv 6 (3ª) opt.", "key": "r6c_dom" }]
        },
        {
          "date": "Lun 30/3",
          "isoDate": "2026-03-30",
          "alt": true,
          "badges": [{ "cls": "b-opt", "txt": "Lv 6 (3ª) alt. / mob.", "key": "r6c_lun" }]
        }
      ]
    },
    {
      "piano": "apr2026",
      "label": "Sett. 2  31 mar–6 apr",
      "note": "Livello 7 — 3 sessioni. Il salto più impegnativo del piano (15'→25'). 3 corse, 2 forza, 1 arrampicata. Con 5 settimane hai il lusso di consolidare ogni livello senza fretta.",
      "cols": 7,
      "days": [
        {
          "date": "Mar 31/3",
          "isoDate": "2026-03-31",
          "badges": [{ "cls": "b-run", "txt": "Corsa Lv 7 (1ª)", "key": "r7a" }]
        },
        {
          "date": "Mer 1/4",
          "isoDate": "2026-04-01",
          "badges": [{ "cls": "b-mob", "txt": "Mobilità", "key": "mob2" }]
        },
        {
          "date": "Gio 2/4",
          "isoDate": "2026-04-02",
          "badges": [{ "cls": "b-forza", "txt": "Forza gambe A", "key": "f2a" }]
        },
        {
          "date": "Ven 3/4",
          "isoDate": "2026-04-03",
          "badges": [{ "cls": "b-run", "txt": "Corsa Lv 7 (2ª)", "key": "r7b" }]
        },
        {
          "date": "Sab 4/4",
          "isoDate": "2026-04-04",
          "badges": [{ "cls": "b-climb", "txt": "Arrampicata", "key": "c2" }]
        },
        {
          "date": "Dom 5/4",
          "isoDate": "2026-04-05",
          "badges": [
            { "cls": "b-run", "txt": "Lv 7 (3ª)", "key": "r7c" },
            { "cls": "b-forza", "txt": "Forza B (opt.)", "key": "f2b" }
          ]
        },
        {
          "date": "Lun 6/4",
          "isoDate": "2026-04-06",
          "badges": [],
          "rest": true
        }
      ]
    },
    {
      "piano": "apr2026",
      "label": "Sett. 3  7–13 apr",
      "note": "⚡ Picco — Livello 8 + forza al massimo volume. ATTENZIONE: il 7 apr è martedì. 2 corse Lv 8, 2 forza, 1 arrampicata. Se giovedì sei stanco, la forza B del venerdì si riduce a 2 giri.",
      "cols": 7,
      "days": [
        {
          "date": "Mar 7/4",
          "isoDate": "2026-04-07",
          "badges": [{ "cls": "b-run", "txt": "Corsa Lv 8 (1ª)", "key": "r8a" }]
        },
        {
          "date": "Mer 8/4",
          "isoDate": "2026-04-08",
          "badges": [{ "cls": "b-mob", "txt": "Recupero attivo", "key": "mob3" }]
        },
        {
          "date": "Gio 9/4",
          "isoDate": "2026-04-09",
          "badges": [{ "cls": "b-forza", "txt": "Forza gambe A", "key": "f3a" }]
        },
        {
          "date": "Ven 10/4",
          "isoDate": "2026-04-10",
          "badges": [{ "cls": "b-run", "txt": "Corsa Lv 8 (2ª)", "key": "r8b" }]
        },
        {
          "date": "Sab 11/4",
          "isoDate": "2026-04-11",
          "badges": [{ "cls": "b-forza", "txt": "Forza gambe B", "key": "f3b" }]
        },
        {
          "date": "Dom 12/4",
          "isoDate": "2026-04-12",
          "badges": [{ "cls": "b-climb", "txt": "Arrampicata", "key": "c3" }]
        },
        {
          "date": "Lun 13/4",
          "isoDate": "2026-04-13",
          "badges": [],
          "rest": true
        }
      ]
    },
    {
      "piano": "apr2026",
      "label": "Sett. 4  14–19 apr",
      "note": "Livello 9 — fino a 3 sessioni. Forza scende a 1 sessione: il volume di corsa è già alto. I 45' continui sono la distanza più lunga del piano: consolidarli qui costruisce la fiducia per la gara.",
      "cols": 6,
      "days": [
        {
          "date": "Mar 14/4",
          "isoDate": "2026-04-14",
          "badges": [{ "cls": "b-run", "txt": "Corsa Lv 9 (1ª)", "key": "r9a" }]
        },
        {
          "date": "Mer 15/4",
          "isoDate": "2026-04-15",
          "badges": [{ "cls": "b-mob", "txt": "Mobilità", "key": "mob4" }]
        },
        {
          "date": "Gio 16/4",
          "isoDate": "2026-04-16",
          "badges": [{ "cls": "b-climb", "txt": "Arrampicata", "key": "c4" }]
        },
        {
          "date": "Ven 17/4",
          "isoDate": "2026-04-17",
          "badges": [{ "cls": "b-run", "txt": "Corsa Lv 9 (2ª)", "key": "r9b" }]
        },
        {
          "date": "Sab 18/4",
          "isoDate": "2026-04-18",
          "badges": [{ "cls": "b-forza", "txt": "Forza gambe", "key": "f4a" }]
        },
        {
          "date": "Dom 19/4",
          "isoDate": "2026-04-19",
          "alt": true,
          "badges": [{ "cls": "b-opt", "txt": "Lv 9 (3ª) opt.", "key": "r9c" }]
        }
      ]
    },
    {
      "piano": "apr2026",
      "label": "Sett. 5  20–26 apr — Scarico",
      "note": "🏁 Scarico e gara domenica 26 aprile. 2 corse brevi, 1 forza leggerissima, arrampicata facile, mobilità. Sabato 25: riposo serale e sonno. Il lavoro è fatto.",
      "cols": 7,
      "days": [
        {
          "date": "Lun 20/4",
          "isoDate": "2026-04-20",
          "badges": [],
          "rest": true
        },
        {
          "date": "Mar 21/4",
          "isoDate": "2026-04-21",
          "badges": [{ "cls": "b-run", "txt": "Corsa easy 20 min", "key": "rsca" }]
        },
        {
          "date": "Mer 22/4",
          "isoDate": "2026-04-22",
          "badges": [{ "cls": "b-forza", "txt": "Forza scarico", "key": "f5" }]
        },
        {
          "date": "Gio 23/4",
          "isoDate": "2026-04-23",
          "badges": [{ "cls": "b-climb", "txt": "Arrampicata facile", "key": "c5" }]
        },
        {
          "date": "Ven 24/4",
          "isoDate": "2026-04-24",
          "badges": [{ "cls": "b-run", "txt": "Corsa 15 min + strides", "key": "rscb" }]
        },
        {
          "date": "Sab 25/4",
          "isoDate": "2026-04-25",
          "badges": [{ "cls": "b-mob", "txt": "Mobilità pre-gara", "key": "mob5" }]
        },
        {
          "date": "Dom 26/4 🏁",
          "isoDate": "2026-04-26",
          "badges": [{ "cls": "b-gara", "txt": "🏁 GARA 10 km", "key": "r10" }]
        }
      ]
    }
  ]
}
